glas/__init__.py
glas/glas.py
glas-0.1.0.dist-info/LICENSE
glas-0.1.0.dist-info/METADATA
glas-0.1.0.dist-info/WHEEL
glas-0.1.0.dist-info/top_level.txt
glas-0.1.0.dist-info/RECORD
