Metadata-Version: 2.1
Name: glas
Version: 0.1.0
Summary: Python module for solving the inverse design of materials
Home-page: https://github.com/drcassar/glas
Author: Daniel Roberto Cassar
Author-email: contact@danielcassar.com.br
License: GPL
Keywords: materials design,inverse design,genetic algorithm
Platform: UNKNOWN
Classifier: Programming Language :: Python :: 3.6
Classifier: Programming Language :: Python :: 3.7
Classifier: Programming Language :: Python :: 3.8
Classifier: License :: OSI Approved :: GNU General Public License v3 or later (GPLv3+)
Classifier: Operating System :: OS Independent
Classifier: Topic :: Scientific/Engineering
Classifier: Intended Audience :: Science/Research
Classifier: Environment :: Console
Requires-Python: >=3.6
Requires-Dist: deap
